{"namedChunkGroups":{"polyfill":{"name":"polyfill","assets":[{"name":"webpack-runtime-38fff23c37f01943ef1e.js","size":4100},{"name":"polyfill-c64b171993bb26b718fb.js","size":82617}],"filteredAssets":0,"assetsSize":86717,"filteredAuxiliaryAssets":2,"auxiliaryAssetsSize":217310},"app":{"name":"app","assets":[{"name":"webpack-runtime-38fff23c37f01943ef1e.js","size":4100},{"name":"framework-8422a4916cf7e29be454.js","size":129739},{"name":"styles.e7ced8ae4f2f99301fb4.css","size":6442},{"name":"app-e32263c2bbddfb2b2da0.js","size":77305}],"filteredAssets":0,"assetsSize":217586,"filteredAuxiliaryAssets":3,"auxiliaryAssetsSize":673998},"component---src-components-blog-template-js":{"name":"component---src-components-blog-template-js","assets":[{"name":"commons-729e203b1c2bb0323463.js","size":15746},{"name":"component---src-components-blog-template-js-cb8829d891b17475aa87.js","size":6285}],"filteredAssets":0,"assetsSize":22031,"filteredAuxiliaryAssets":2,"auxiliaryAssetsSize":81674},"component---src-pages-404-js":{"name":"component---src-pages-404-js","assets":[{"name":"commons-729e203b1c2bb0323463.js","size":15746},{"name":"component---src-pages-404-js-ad80622b10fd27e8de85.js","size":1055}],"filteredAssets":0,"assetsSize":16801,"filteredAuxiliaryAssets":2,"auxiliaryAssetsSize":66747},"component---src-pages-blogs-js":{"name":"component---src-pages-blogs-js","assets":[{"name":"commons-729e203b1c2bb0323463.js","size":15746},{"name":"component---src-pages-blogs-js-9e12490df651af0626cf.js","size":2411}],"filteredAssets":0,"assetsSize":18157,"filteredAuxiliaryAssets":2,"auxiliaryAssetsSize":71090},"component---src-pages-index-js":{"name":"component---src-pages-index-js","assets":[{"name":"commons-729e203b1c2bb0323463.js","size":15746},{"name":"component---src-pages-index-js-62c923550bc047239241.js","size":4111}],"filteredAssets":0,"assetsSize":19857,"filteredAuxiliaryAssets":2,"auxiliaryAssetsSize":75597},"component---src-pages-privacy-js":{"name":"component---src-pages-privacy-js","assets":[{"name":"commons-729e203b1c2bb0323463.js","size":15746},{"name":"component---src-pages-privacy-js-4ca0280f72dfec456a04.js","size":2281}],"filteredAssets":0,"assetsSize":18027,"filteredAuxiliaryAssets":2,"auxiliaryAssetsSize":68296}},"assetsByChunkName":{"polyfill":["webpack-runtime-38fff23c37f01943ef1e.js","polyfill-c64b171993bb26b718fb.js"],"app":["webpack-runtime-38fff23c37f01943ef1e.js","framework-8422a4916cf7e29be454.js","styles.e7ced8ae4f2f99301fb4.css","app-e32263c2bbddfb2b2da0.js"],"component---src-components-blog-template-js":["commons-729e203b1c2bb0323463.js","component---src-components-blog-template-js-cb8829d891b17475aa87.js"],"component---src-pages-404-js":["commons-729e203b1c2bb0323463.js","component---src-pages-404-js-ad80622b10fd27e8de85.js"],"component---src-pages-blogs-js":["commons-729e203b1c2bb0323463.js","component---src-pages-blogs-js-9e12490df651af0626cf.js"],"component---src-pages-index-js":["commons-729e203b1c2bb0323463.js","component---src-pages-index-js-62c923550bc047239241.js"],"component---src-pages-privacy-js":["commons-729e203b1c2bb0323463.js","component---src-pages-privacy-js-4ca0280f72dfec456a04.js"]},"childAssetsByChunkName":{}}